[
  {
    "id": "qz-commentaire-intro-ordre",
    "module": "methode-commentaire",
    "category": "methode",
    "type": "ordering",
    "statement": "Remets dans l'ordre les éléments de l'introduction d'un commentaire.",
    "items": [
      "Accroche (contexte, genre, mouvement)",
      "Présentation du texte (auteur, œuvre, date)",
      "Situation de l'extrait",
      "Problématique",
      "Annonce du plan"
    ],
    "explanation": "On part du général (accroche) pour amener le texte, on le présente et le situe, puis on pose la problématique avant d'annoncer le plan.",
    "difficulty": 2,
    "tags": ["introduction"]
  },
  {
    "id": "qz-commentaire-paragraphe-ordre",
    "module": "methode-commentaire",
    "category": "methode",
    "type": "ordering",
    "statement": "Remets dans l'ordre les étapes d'un paragraphe d'analyse.",
    "items": [
      "Idée directrice",
      "Citation / relevé du texte",
      "Identification du procédé",
      "Interprétation de l'effet"
    ],
    "explanation": "On annonce l'idée, on l'appuie sur une citation, on nomme le procédé, puis on interprète l'effet.",
    "difficulty": 2,
    "tags": ["paragraphe"]
  },
  {
    "id": "qz-commentaire-eviter",
    "module": "methode-commentaire",
    "category": "methode",
    "type": "qcm",
    "statement": "Quelle erreur est la plus pénalisée dans un commentaire ?",
    "choices": [
      "Citer le texte entre guillemets",
      "La paraphrase (redire le texte sans l'analyser)",
      "Nommer les procédés",
      "Annoncer un plan en deux axes"
    ],
    "answer": 1,
    "explanation": "Le commentaire doit **analyser**, pas redire le texte : la **paraphrase** est la faute majeure.",
    "difficulty": 1,
    "tags": ["paraphrase"]
  },
  {
    "id": "qz-commentaire-conclusion",
    "module": "methode-commentaire",
    "category": "methode",
    "type": "qcm",
    "statement": "Que contient la conclusion d'un commentaire ?",
    "choices": [
      "Une nouvelle analyse de procédé",
      "Un résumé du texte",
      "Un bilan répondant à la problématique, puis une ouverture",
      "La problématique seulement"
    ],
    "answer": 2,
    "explanation": "La conclusion fait le **bilan** (réponse à la problématique) puis propose une **ouverture**, sans analyse nouvelle.",
    "difficulty": 1,
    "tags": ["conclusion"]
  },
  {
    "id": "qz-commentaire-axe",
    "module": "methode-commentaire",
    "category": "methode",
    "type": "qcm",
    "statement": "Qu'est-ce qu'un « axe de lecture » dans un commentaire ?",
    "choices": [
      "Une ligne du texte choisie au hasard",
      "Une grande partie du développement, organisée autour d'une interprétation d'ensemble",
      "La biographie de l'auteur",
      "Un synonyme de citation"
    ],
    "answer": 1,
    "explanation": "Un axe de lecture est une **grande partie** du développement, fédérée par une interprétation que l'on démontre à l'aide de procédés.",
    "difficulty": 2,
    "tags": ["plan", "axe"]
  }
]
